moosepy/__init__.py
moosepy/moosepy.py
moosepy-1.0.dist-info/METADATA
moosepy-1.0.dist-info/WHEEL
moosepy-1.0.dist-info/top_level.txt
moosepy-1.0.dist-info/RECORD
