Metadata-Version: 2.1
Name: moosepy
Version: 1.0
Summary: Controller library for robotmoose robots.
Home-page: https://github.com/robotmoose/robotmoose
Author: Ryan Stonebraker, Tristan Van Cise, Dain Harmon, Frank Cline
Author-email: ryanastonebraker@gmail.com
License: UNKNOWN
Platform: UNKNOWN
Classifier: Programming Language :: Python :: 3
Classifier: License :: OSI Approved :: Apache Software License
Classifier: Operating System :: OS Independent
Requires-Dist: requests
